graphs_ldavismi/__init__.py
graphs_ldavismi/heapq.py
graphs_ldavismi/sp.py
graphs_ldavismi-0.0.3.dist-info/METADATA
graphs_ldavismi-0.0.3.dist-info/WHEEL
graphs_ldavismi-0.0.3.dist-info/RECORD
