Metadata-Version: 2.3
Name: graphs_ldavismi
Version: 0.0.3
Summary: A small package containing Dijkstra's Shortest Path Algorithm
Project-URL: Homepage, https://github.com/pypa/sampleproject
Project-URL: Bug Tracker, https://github.com/pypa/sampleproject/issues
Author-email: Logan Davis-Miller <ldavismi@msudenver.edu>
Classifier: License :: OSI Approved :: MIT License
Classifier: Operating System :: OS Independent
Classifier: Programming Language :: Python :: 3
Requires-Python: >=3.7
